speedcheck/__init__.py
speedcheck/__main__.py
speedcheck/speedcheck.py
speedcheck/speedtest_cflare.py
speedcheck/speedtest_fast.py
speedcheck/speedtest_mlab.py
speedcheck/speedtest_ookla.py
speedcheck/speedtest_openspeedtest.py
speedcheck/speedtest_speedsmart.py
speedcheck-0.0.5.dist-info/LICENSE
speedcheck-0.0.5.dist-info/METADATA
speedcheck-0.0.5.dist-info/WHEEL
speedcheck-0.0.5.dist-info/entry_points.txt
speedcheck-0.0.5.dist-info/top_level.txt
speedcheck-0.0.5.dist-info/RECORD
